LICENSE
MANIFEST.in
README.md
setup.cfg
setup.py
ringo_news/__init__.py
ringo_news/model.py
ringo_news/news.json
ringo_news/news.xml
ringo_news/views.py
ringo_news.egg-info/PKG-INFO
ringo_news.egg-info/SOURCES.txt
ringo_news.egg-info/dependency_links.txt
ringo_news.egg-info/entry_points.txt
ringo_news.egg-info/not-zip-safe
ringo_news.egg-info/requires.txt
ringo_news.egg-info/top_level.txt
ringo_news/locale/README
ringo_news/locale/ringo_news.pot
ringo_news/locale/de/LC_MESSAGES/ringo_news.po
ringo_news/scripts/__init__.py
ringo_news/scripts/command.py
ringo_news/templates/newslist.mako