Metadata-Version: 1.0
Name: ringo-news
Version: 1.0
Summary: News extension for the ringo framework
Home-page: https://github.com/ringo-framework/ringo_news
Author: Torsten Irländer
Author-email: torsten.irlaender@googlemail.com
License: GPL
Keywords: ringo pyramid extension
Platform: UNKNOWN
